Examples.py
RoboPandas.py
RobotFramework_Examples-1.1.0.dist-info/LICENSE
RobotFramework_Examples-1.1.0.dist-info/METADATA
RobotFramework_Examples-1.1.0.dist-info/WHEEL
RobotFramework_Examples-1.1.0.dist-info/top_level.txt
RobotFramework_Examples-1.1.0.dist-info/RECORD
