Metadata-Version: 2.1
Name: RobotFramework-Examples
Version: 1.1.0
Summary: Examples in Robot Framework. Expands example data to individual test cases
Author: Vernon Crabtree
Author-email: vernon.b.crabtree@gmail.com
License: Apache License 2.0
Project-URL: Examples, https://github.com/worldline/RobotFramework-Examples
Keywords: robotframework testing testautomation bdd gwen examples
Platform: any
Classifier: License :: OSI Approved :: Apache Software License
Classifier: Operating System :: OS Independent
Classifier: Programming Language :: Python
Classifier: Programming Language :: Python :: 3
Classifier: Programming Language :: Python :: 3.6
Classifier: Programming Language :: Python :: 3.7
Classifier: Programming Language :: Python :: 3.8
Classifier: Programming Language :: Python :: 3.9
Classifier: Programming Language :: Python :: 3 :: Only
Classifier: Topic :: Software Development :: Testing
Classifier: Framework :: Robot Framework
Classifier: Framework :: Robot Framework :: Library
Requires-Python: >=3.8
License-File: LICENSE
Requires-Dist: robotframework
Requires-Dist: pandas
Requires-Dist: sqlalchemy
Requires-Dist: docutils
